{
    "description": "DO NOT DELETE THIS FILE. This file is used to keep track of which files have been synced in the most recent deployment. If you delete this file a resync will need to be done (which can take a while) - read more: https://github.com/SamKirkland/FTP-Deploy-Action",
    "version": "1.0.0",
    "generatedTime": 1749341203883,
    "data": [
        {
            "type": "file",
            "name": "Documentation.txt",
            "size": 121,
            "hash": "87cca8968f6d5db6df05106b233af2ca81ce9e715fd0646201d00fe5ef434ca0"
        },
        {
            "type": "file",
            "name": "README.md",
            "size": 1675,
            "hash": "56c0c7471223f30f03df38476e98cc279b648bf4438a00020ef06324facfcb34"
        },
        {
            "type": "file",
            "name": "composer-setup.php",
            "size": 58444,
            "hash": "8586e7c8ce2839946a253a9ca3284e525245c1f82d8bd1e221cef88a59d00a75"
        },
        {
            "type": "file",
            "name": "composer.json",
            "size": 66,
            "hash": "6961a02d41bdb58a0414e7beb1180bf883be390c190f86acebf0184958c10261"
        },
        {
            "type": "file",
            "name": "composer.lock",
            "size": 4126,
            "hash": "51d5042ea464a00396866ed04a1924f065f0df9bb0ee4673f0e22ed5c5ecea6b"
        },
        {
            "type": "file",
            "name": "composer.phar",
            "size": 3125568,
            "hash": "8e8829ec2b97fcb05158236984bc252bef902e7b8ff65555a1eeda4ec13fb82b"
        },
        {
            "type": "folder",
            "name": "config"
        },
        {
            "type": "file",
            "name": "index.php",
            "size": 14412,
            "hash": "3da91435985557135be19b6b001dfdf68b36819b348ee4031e5dc91f7fdc8f5b"
        },
        {
            "type": "folder",
            "name": "modules"
        },
        {
            "type": "file",
            "name": "opening.php",
            "size": 8405,
            "hash": "fb8a50e122e3d864540b23cc153a636d68edaf7dd6feedf4f230d0773cdbb8b1"
        },
        {
            "type": "folder",
            "name": "public"
        },
        {
            "type": "folder",
            "name": "src"
        },
        {
            "type": "folder",
            "name": "vendor"
        },
        {
            "type": "folder",
            "name": "config/bd"
        },
        {
            "type": "file",
            "name": "config/conn.php",
            "size": 407,
            "hash": "b8f9fd49eab51e226877418206239d3137f5cbdb6d263c914f75a8a22843fd39"
        },
        {
            "type": "file",
            "name": "config/cryp2graph2.php",
            "size": 1745,
            "hash": "e75ed3557e95c1561935217fab55a6c3d51e0b9b7d1b49504b41db3d47f8f568"
        },
        {
            "type": "file",
            "name": "config/functions.php",
            "size": 0,
            "hash": "e3b0c44298fc1c149afbf4c8996fb92427ae41e4649b934ca495991b7852b855"
        },
        {
            "type": "folder",
            "name": "modules/admin"
        },
        {
            "type": "file",
            "name": "public/index.php",
            "size": 1281,
            "hash": "f8caa2ad5f968940715300ad0a30041393487d8077c23678d7634fd1fa2706e7"
        },
        {
            "type": "file",
            "name": "public/index_wblockacess.php",
            "size": 4484,
            "hash": "a7c055557a4519b69095eab281f81f07f11a858de8448b42ba48c961001fc6e5"
        },
        {
            "type": "folder",
            "name": "src/assets"
        },
        {
            "type": "folder",
            "name": "src/components"
        },
        {
            "type": "file",
            "name": "vendor/autoload.php",
            "size": 748,
            "hash": "d8e6b2e2b2cbebb67927cdbaac64cdba7209cc995625fa5e4ca1b73a42abdb9a"
        },
        {
            "type": "folder",
            "name": "vendor/composer"
        },
        {
            "type": "folder",
            "name": "vendor/phpmailer"
        },
        {
            "type": "file",
            "name": "config/bd/IFApoia.sql",
            "size": 3572,
            "hash": "0302c05426c73cd2240291e5db0973ce13e311d834a5e9d3ded9f43c664e15b6"
        },
        {
            "type": "file",
            "name": "modules/admin/admin.php",
            "size": 217,
            "hash": "f89ed452cead7624db642c222138c74ac61277da5930e98dad3899b864d6ecbf"
        },
        {
            "type": "folder",
            "name": "src/assets/css"
        },
        {
            "type": "folder",
            "name": "src/assets/icons"
        },
        {
            "type": "folder",
            "name": "src/assets/img"
        },
        {
            "type": "folder",
            "name": "src/assets/js"
        },
        {
            "type": "file",
            "name": "src/components/footer.php",
            "size": 239,
            "hash": "2eaf943b1389b73db7b4c1fe3007fee2c4693cc0c76a892b5a967c7663c45571"
        },
        {
            "type": "file",
            "name": "src/components/header.php",
            "size": 8239,
            "hash": "edc3e24dd1fd7262bc10220fb2ed375503446bffb6771a42b9a94d696dc3e0ef"
        },
        {
            "type": "file",
            "name": "src/components/login.php",
            "size": 47302,
            "hash": "f21de6570832184febf18e9e1edb276942b795fcdc43bf8630d6fa41f820e3e0"
        },
        {
            "type": "file",
            "name": "src/components/logout.php",
            "size": 132,
            "hash": "5a42563685796b339285429e35a2b78e7fa0baa6c24e356e1bca736bbc2d526d"
        },
        {
            "type": "file",
            "name": "src/components/nav_bar.php",
            "size": 2372,
            "hash": "8eb994fa064c9edab87aaf56ce399690c250b4df98885c55a56319566cb42738"
        },
        {
            "type": "file",
            "name": "vendor/composer/ClassLoader.php",
            "size": 16378,
            "hash": "d4b2313e562edf942838ec316d983c1a3459ca67da3e5658e861200b0b3693c2"
        },
        {
            "type": "file",
            "name": "vendor/composer/InstalledVersions.php",
            "size": 17395,
            "hash": "1e4525198301d1ed1f87ac3df2a8555a6f139f8df30a703d0b775a61963c96e4"
        },
        {
            "type": "file",
            "name": "vendor/composer/LICENSE",
            "size": 1070,
            "hash": "c8cce4b6b9729f264ffdf9296d505d63432497feeed1f586d1902b942197e024"
        },
        {
            "type": "file",
            "name": "vendor/composer/autoload_classmap.php",
            "size": 222,
            "hash": "375085d0d6690301081436cd75755cb2c882f8a7f6fc385c8814a11734fc413a"
        },
        {
            "type": "file",
            "name": "vendor/composer/autoload_namespaces.php",
            "size": 139,
            "hash": "ede505407590638a435137f4e060136f1008de79fc169b3de9793423b0cea38c"
        },
        {
            "type": "file",
            "name": "vendor/composer/autoload_psr4.php",
            "size": 213,
            "hash": "37fe79fff76d924ed6640c7d700bdd0f35cfc736587f0fc3d6ead4649ce2eeb3"
        },
        {
            "type": "file",
            "name": "vendor/composer/autoload_real.php",
            "size": 1137,
            "hash": "f379b22b0976de306815a501b80d1ed3772385b4904666cad4491d1dc330fa55"
        },
        {
            "type": "file",
            "name": "vendor/composer/autoload_static.php",
            "size": 1093,
            "hash": "f57137af1426f4cd677b1294322f379b4184c6258ea9f00d754b7677cc3ae055"
        },
        {
            "type": "file",
            "name": "vendor/composer/installed.json",
            "size": 3767,
            "hash": "75f2d7a0c6c9924932608afbe60b66c5f950b1433efae081a0e355c8ab165a83"
        },
        {
            "type": "file",
            "name": "vendor/composer/installed.php",
            "size": 1108,
            "hash": "b5a9fccbc65a3e7390ea49dedfbd5d6da17ff00419059ac64f6b2f0b616d12fa"
        },
        {
            "type": "file",
            "name": "vendor/composer/platform_check.php",
            "size": 925,
            "hash": "680f7726ea57d47a1ab675dba38cbdb25e135dca8124583024361f67157c8b1a"
        },
        {
            "type": "folder",
            "name": "vendor/phpmailer/phpmailer"
        },
        {
            "type": "file",
            "name": "src/assets/css/style.css",
            "size": 12830,
            "hash": "5bdb823ce80f837e201961ae882c8af0961d23a6ac810c7d8e7d5b8a3621a2e0"
        },
        {
            "type": "file",
            "name": "src/assets/icons/add-large-line.svg",
            "size": 289,
            "hash": "e0c4cc413f9f7b2e066a9cc2901ff94179c657b1f0a11f6f76ec6c1e74f08319"
        },
        {
            "type": "file",
            "name": "src/assets/icons/android-chrome-192x192.png",
            "size": 21757,
            "hash": "3cc86109ab5cff4daabaf775dc2e1da3623f5eec0659ff2b63df47715c0945ad"
        },
        {
            "type": "file",
            "name": "src/assets/icons/arrow_down.svg",
            "size": 252,
            "hash": "4c3f0f7d9622a42e100e9b2a30d39b6081af6c2190f99e80a08ea62e8da45805"
        },
        {
            "type": "file",
            "name": "src/assets/icons/close_search_btn.svg",
            "size": 305,
            "hash": "c22c43df4d1d88da50705ac13a78dfb23981d7611acd59777e0037528be9c6a4"
        },
        {
            "type": "file",
            "name": "src/assets/icons/icon_usuario.svg",
            "size": 428,
            "hash": "a2e0ff404d4b68df8c7c4373279a7f02b7331928bb82f55b90af937730f36bec"
        },
        {
            "type": "folder",
            "name": "src/assets/icons/favicon"
        },
        {
            "type": "file",
            "name": "src/assets/icons/menu-line.svg",
            "size": 152,
            "hash": "9071ffaeac807a49e6a54c2c725e07d71293789ac1603907c727e89c111ce439"
        },
        {
            "type": "file",
            "name": "src/assets/icons/notification-line.svg",
            "size": 326,
            "hash": "332acce38c9f6520b28034bcecf134fc838aa24b0b9285b959404fad7d976526"
        },
        {
            "type": "file",
            "name": "src/assets/img/Logotipo_antiga.png",
            "size": 428899,
            "hash": "06463875985fd2ae005d616c63953f61529ca4f1c80e267282642dac9347bdb4"
        },
        {
            "type": "file",
            "name": "src/assets/img/default-user.png",
            "size": 36942,
            "hash": "a5778e3ff74cf8ea5de38939339c61808970a9f000e922f2fbdb45496d127fb7"
        },
        {
            "type": "file",
            "name": "src/assets/img/favicon.png",
            "size": 22153,
            "hash": "6e6f771f2be4a46c1fcbaf820d3ca2355004a04f8812c64f8337d1aafb292e8e"
        },
        {
            "type": "file",
            "name": "src/assets/img/ifcampus.jpg",
            "size": 443429,
            "hash": "26b993def275128d2c2b5068b26860929cc14f6982721e263608d64be157f306"
        },
        {
            "type": "file",
            "name": "src/assets/js/javascript.js",
            "size": 1761,
            "hash": "e7655e819c0ab0b3fefa74349cafb14d9bb434860480fdc3ddc587c14143b311"
        },
        {
            "type": "file",
            "name": "vendor/phpmailer/phpmailer/COMMITMENT",
            "size": 2092,
            "hash": "340ae872d625b128586b8751f3d599f63893417d8867cdb488702c48ea58fbc1"
        },
        {
            "type": "file",
            "name": "vendor/phpmailer/phpmailer/LICENSE",
            "size": 26529,
            "hash": "a1a33180d02960ab1c5de36cf20b1a2f0fe9888d83826ad263da5db52f1b183b"
        },
        {
            "type": "file",
            "name": "vendor/phpmailer/phpmailer/README.md",
            "size": 16832,
            "hash": "931b572c8e9eed769388f627874690b8ac1a95983749ca8c760c96244b75ce6b"
        },
        {
            "type": "file",
            "name": "vendor/phpmailer/phpmailer/SECURITY.md",
            "size": 7585,
            "hash": "748329021e3d7307694d5c0e108dd8a31850e58ac96bc6de6cf1099568906eca"
        },
        {
            "type": "file",
            "name": "vendor/phpmailer/phpmailer/SMTPUTF8.md",
            "size": 5915,
            "hash": "eb3409266849cdb958db6d939b70a31097767f87e0e1003353528a746423a013"
        },
        {
            "type": "file",
            "name": "vendor/phpmailer/phpmailer/VERSION",
            "size": 7,
            "hash": "81254ec8251acd235eecc3375f5dc6931a9fd2c4405b0c2e2760aaa7b960307b"
        },
        {
            "type": "file",
            "name": "vendor/phpmailer/phpmailer/composer.json",
            "size": 2775,
            "hash": "988c74b659c07ecc32f6473ee151eb808a7f74cb1e3c3e2f14562caaf9c5785a"
        },
        {
            "type": "file",
            "name": "vendor/phpmailer/phpmailer/get_oauth_token.php",
            "size": 6261,
            "hash": "9564843fbfc9f153e464849e736d08cb41f124f1acb2fcd6c129d50be14d52b8"
        },
        {
            "type": "folder",
            "name": "vendor/phpmailer/phpmailer/language"
        },
        {
            "type": "folder",
            "name": "vendor/phpmailer/phpmailer/src"
        },
        {
            "type": "file",
            "name": "src/assets/icons/favicon/android-chrome-192x192.png",
            "size": 21757,
            "hash": "3cc86109ab5cff4daabaf775dc2e1da3623f5eec0659ff2b63df47715c0945ad"
        },
        {
            "type": "file",
            "name": "src/assets/icons/favicon/android-chrome-512x512.png",
            "size": 94605,
            "hash": "a7e38886e6f3726f5f2453f9a417cdf12813abcbadb259e94a00d604faf1481b"
        },
        {
            "type": "file",
            "name": "src/assets/icons/favicon/apple-touch-icon.png",
            "size": 19591,
            "hash": "9afb860213e08f67741f7e0ddbda0ab2e073d6180bc72308a64e73e07ffc112d"
        },
        {
            "type": "file",
            "name": "src/assets/icons/favicon/favicon-16x16.png",
            "size": 594,
            "hash": "98977a5b749d3793795e16b4c4c11a37f5081ce421233c2187b7abb6b54ca09e"
        },
        {
            "type": "file",
            "name": "src/assets/icons/favicon/favicon-32x32.png",
            "size": 1466,
            "hash": "6e8b201e437ba4e49c541c739e29601069f34fae7c972a958a507255752a84d6"
        },
        {
            "type": "file",
            "name": "src/assets/icons/favicon/favicon.ico",
            "size": 152126,
            "hash": "849ce7a346a74d449c3287f33248ee35f335a4615754a5fadcdde92964e2b52f"
        },
        {
            "type": "file",
            "name": "src/assets/icons/favicon/site.webmanifest",
            "size": 263,
            "hash": "7a9e07ce1f7386689917602ddc5a75750ad842e605ff764f67173529c181bf04"
        },
        {
            "type": "file",
            "name": "vendor/phpmailer/phpmailer/language/phpmailer.lang-af.php",
            "size": 1584,
            "hash": "d4c5272712f1b1cd6b3d08f83a89fbdae257de308a58e6eee1f4e7f519c86062"
        },
        {
            "type": "file",
            "name": "vendor/phpmailer/phpmailer/language/phpmailer.lang-ar.php",
            "size": 2024,
            "hash": "ad11ffbf21f84fe6e812a0cf4f82df4412dd232ab6f6b6fe47e2c760845ec04f"
        },
        {
            "type": "file",
            "name": "vendor/phpmailer/phpmailer/language/phpmailer.lang-as.php",
            "size": 3792,
            "hash": "8aaaa3925b2e79a475ffd7b65e29406b1e86c8ea48a666ec32243668f5e28494"
        },
        {
            "type": "file",
            "name": "vendor/phpmailer/phpmailer/language/phpmailer.lang-az.php",
            "size": 1749,
            "hash": "8b116561af83e2bd1ef3319ff8103f169883e89efab592115d98c9ae7c09d6df"
        },
        {
            "type": "file",
            "name": "vendor/phpmailer/phpmailer/language/phpmailer.lang-ba.php",
            "size": 1745,
            "hash": "df573ba9a9431bff2c602b7b297040e0f9cf9b319562f17c686f01f1ed4ebfad"
        },
        {
            "type": "file",
            "name": "vendor/phpmailer/phpmailer/language/phpmailer.lang-be.php",
            "size": 2178,
            "hash": "47c51cef7371142b993b58764c0abd4e82fe7213f9bd85b6dcfb24d0acd223ec"
        },
        {
            "type": "file",
            "name": "vendor/phpmailer/phpmailer/language/phpmailer.lang-bg.php",
            "size": 2196,
            "hash": "9a556b5ad45ead80d7331f5ed713799e7fb810c52f8d7913725585fbeff084c2"
        },
        {
            "type": "file",
            "name": "vendor/phpmailer/phpmailer/language/phpmailer.lang-bn.php",
            "size": 3845,
            "hash": "ff7842ce6fdc7cbb846b16f292e126fbc578e0c27da48092e4a5f44d928aebe6"
        },
        {
            "type": "file",
            "name": "vendor/phpmailer/phpmailer/language/phpmailer.lang-ca.php",
            "size": 1730,
            "hash": "2b62db0921d2d321c80869bc9544b744747fd7cf398cc17358c0ae0b2533548c"
        },
        {
            "type": "file",
            "name": "vendor/phpmailer/phpmailer/language/phpmailer.lang-cs.php",
            "size": 1798,
            "hash": "4bdb6445032c31fa1c41d65b8840f4fed0c30b96a6e68418ea6968e6de49f664"
        },
        {
            "type": "file",
            "name": "vendor/phpmailer/phpmailer/language/phpmailer.lang-da.php",
            "size": 2409,
            "hash": "32a35e1df4a39d8d4bd7c4daad3a19eae2c139cdb1b58dead36a2b5dc91e83db"
        },
        {
            "type": "file",
            "name": "vendor/phpmailer/phpmailer/language/phpmailer.lang-de.php",
            "size": 1886,
            "hash": "41e9bee22a8b00d42b28ebadae85ba531134a2482108489c0e5ced6ddc25b062"
        },
        {
            "type": "file",
            "name": "vendor/phpmailer/phpmailer/language/phpmailer.lang-el.php",
            "size": 3307,
            "hash": "3760e138e5c0fdc17a896718d2d86239b6d2d936abc0cf016fc5350ee034a8dd"
        },
        {
            "type": "file",
            "name": "vendor/phpmailer/phpmailer/language/phpmailer.lang-eo.php",
            "size": 1665,
            "hash": "d7dc252b77f7a098e4b3c3e7beca875be08b6f01bf68129bc658fce26b06bb31"
        },
        {
            "type": "file",
            "name": "vendor/phpmailer/phpmailer/language/phpmailer.lang-es.php",
            "size": 2588,
            "hash": "6f84a5e4b7fe9fb5867941bb23e21189caaf52b97948a87589132f6bd9ae34f7"
        },
        {
            "type": "file",
            "name": "vendor/phpmailer/phpmailer/language/phpmailer.lang-et.php",
            "size": 1744,
            "hash": "7a854b796bc5058913ab5f5ad489b02ed246ad49220e844a1c3fbb0ffa908fa6"
        },
        {
            "type": "file",
            "name": "vendor/phpmailer/phpmailer/language/phpmailer.lang-fa.php",
            "size": 2079,
            "hash": "7e38e2e75326d9d7bbb87fc4f6dc5c40ce79c9ce43016a707e84af9d7e332102"
        },
        {
            "type": "file",
            "name": "vendor/phpmailer/phpmailer/language/phpmailer.lang-fi.php",
            "size": 1659,
            "hash": "3efb47c9e164860b45ee3a9f707975210d7f87bbc356a7dada075528fc37052c"
        },
        {
            "type": "file",
            "name": "vendor/phpmailer/phpmailer/language/phpmailer.lang-fo.php",
            "size": 1637,
            "hash": "2b778d73170ff1864126bd65839d39098a9dde290e31fe6ea6719b68a030daa2"
        },
        {
            "type": "file",
            "name": "vendor/phpmailer/phpmailer/language/phpmailer.lang-fr.php",
            "size": 2732,
            "hash": "1d816ccae7fa8eea24907686ffeeeeb5861ffdf794690e6a91c142d49d05efd7"
        },
        {
            "type": "file",
            "name": "vendor/phpmailer/phpmailer/language/phpmailer.lang-gl.php",
            "size": 1742,
            "hash": "fe2fd5068446a04e73ca767ca05eba81f6648fcb93988a307a4dbd619054780a"
        },
        {
            "type": "file",
            "name": "vendor/phpmailer/phpmailer/language/phpmailer.lang-he.php",
            "size": 1812,
            "hash": "7d944fe5e073d0dfb8a53cf9f8e9c409d40f5f0149ce6d47c1f4088cb28d69fe"
        },
        {
            "type": "file",
            "name": "vendor/phpmailer/phpmailer/language/phpmailer.lang-hi.php",
            "size": 3768,
            "hash": "2a260e1b5f0d7efbfccc436ea040aa172ecd5ac8ea394482c0dd9a2e7c9d3206"
        },
        {
            "type": "file",
            "name": "vendor/phpmailer/phpmailer/language/phpmailer.lang-hr.php",
            "size": 1754,
            "hash": "b337f280f2e5f087daaa44bd1f359bbc41e01062cbd07a5c67345a45a01ccbaf"
        },
        {
            "type": "file",
            "name": "vendor/phpmailer/phpmailer/language/phpmailer.lang-hu.php",
            "size": 1717,
            "hash": "94045618ef5a86dc4f8176f3ebae3fbb1e29b7ef7cb1ce99ba57ee4724aef3be"
        },
        {
            "type": "file",
            "name": "vendor/phpmailer/phpmailer/language/phpmailer.lang-hy.php",
            "size": 2185,
            "hash": "52fc3f40d24d55ef95702a59ec006c4c5996a22e54a6b00e54a25707db341629"
        },
        {
            "type": "file",
            "name": "vendor/phpmailer/phpmailer/language/phpmailer.lang-id.php",
            "size": 1997,
            "hash": "a9c606b5da1470c02140c96c1ef3fc5ba1175ad0ce119b6f2d93e02c112d2ae1"
        },
        {
            "type": "file",
            "name": "vendor/phpmailer/phpmailer/language/phpmailer.lang-it.php",
            "size": 1819,
            "hash": "06e7faf9dc2dabebe8ea8c684eb9b798ffd241ce039945a8e5583993705b1c3e"
        },
        {
            "type": "file",
            "name": "vendor/phpmailer/phpmailer/language/phpmailer.lang-ja.php",
            "size": 2934,
            "hash": "c1cb38a994fb2f1b523dc622174dd4f7b9e9ba20e8cd864ae44744bd2b8050fc"
        },
        {
            "type": "file",
            "name": "vendor/phpmailer/phpmailer/language/phpmailer.lang-ka.php",
            "size": 2884,
            "hash": "0bf765b1e28e33947df929657c325cd957c506ec42d44d2a32b3d30794f09b31"
        },
        {
            "type": "file",
            "name": "vendor/phpmailer/phpmailer/language/phpmailer.lang-ko.php",
            "size": 1771,
            "hash": "674f7f333694475a3a6164c1c5cb84e25f94a5b0d3118cb49ff2e5a318260c64"
        },
        {
            "type": "file",
            "name": "vendor/phpmailer/phpmailer/language/phpmailer.lang-ku.php",
            "size": 2238,
            "hash": "4cc2ad8c0516ce01090997c802c7cdc3362e974e55ea26823140e60d50328f71"
        },
        {
            "type": "file",
            "name": "vendor/phpmailer/phpmailer/language/phpmailer.lang-lt.php",
            "size": 1627,
            "hash": "ee21a138a136caf9b213b3fe9f070afb9c20f4cdd51178045798bb60ccc82865"
        },
        {
            "type": "file",
            "name": "vendor/phpmailer/phpmailer/language/phpmailer.lang-lv.php",
            "size": 1643,
            "hash": "a986f934cb4a2b9cf5bad1c150f0af9d8a0c7745d36b9904882d68b1bb07fb5d"
        },
        {
            "type": "file",
            "name": "vendor/phpmailer/phpmailer/language/phpmailer.lang-mg.php",
            "size": 1782,
            "hash": "eebd4b1c9caa2b0ad5637b623cad66a0b67363a2e752cbd86eacb2139636fd85"
        },
        {
            "type": "file",
            "name": "vendor/phpmailer/phpmailer/language/phpmailer.lang-mn.php",
            "size": 2186,
            "hash": "e1b246c27568a92fef27a44e9601ce3ff41ca0dac0f564782dc46bfd03f42724"
        },
        {
            "type": "file",
            "name": "vendor/phpmailer/phpmailer/language/phpmailer.lang-ms.php",
            "size": 1734,
            "hash": "f6b8ec01f2734624eadb3e9135e408a5a6da20a5a684b5577d7ba29bddd4b5aa"
        },
        {
            "type": "file",
            "name": "vendor/phpmailer/phpmailer/language/phpmailer.lang-nb.php",
            "size": 2288,
            "hash": "3f7070f004b6f6b3e3c64a6ce63ebe32c861bfbd5bd7c6ddd40c4e19a37fadb8"
        },
        {
            "type": "file",
            "name": "vendor/phpmailer/phpmailer/language/phpmailer.lang-nl.php",
            "size": 2365,
            "hash": "9d43b5bcdd2446f3bc6eea5aec01b7084a9a83ec0c50a73ac968b6c1260dcbe3"
        },
        {
            "type": "file",
            "name": "vendor/phpmailer/phpmailer/language/phpmailer.lang-pl.php",
            "size": 2635,
            "hash": "130beb1aedccab6f9aff7eb76db0e477c40a15485d1eb129555e7d28ec2ee6f9"
        },
        {
            "type": "file",
            "name": "vendor/phpmailer/phpmailer/language/phpmailer.lang-pt.php",
            "size": 2465,
            "hash": "588e547a80a7c867594f2e956ca12625d3b48446b16cd0e47f48fea71ef3ed2c"
        },
        {
            "type": "file",
            "name": "vendor/phpmailer/phpmailer/language/phpmailer.lang-pt_br.php",
            "size": 2719,
            "hash": "8965d817b5667787efd6ffe58b15af236e51ff085594562fafccaf85d9f1bcd8"
        },
        {
            "type": "file",
            "name": "vendor/phpmailer/phpmailer/language/phpmailer.lang-ro.php",
            "size": 2448,
            "hash": "f0cf6c8032723215293095e7a9b2f2a9c1159bb51221511efb6163f4096b9232"
        },
        {
            "type": "file",
            "name": "vendor/phpmailer/phpmailer/language/phpmailer.lang-ru.php",
            "size": 3297,
            "hash": "981aa0630326df0b5dd48da086c19c4a329571a7426c36f6e08ff6470f24687d"
        },
        {
            "type": "file",
            "name": "vendor/phpmailer/phpmailer/language/phpmailer.lang-si.php",
            "size": 3425,
            "hash": "502364f4ccb0c546093c13b4fc2a9ef15e0d47b4e4b789729d72b6cb33c6871e"
        },
        {
            "type": "file",
            "name": "vendor/phpmailer/phpmailer/language/phpmailer.lang-sk.php",
            "size": 1909,
            "hash": "b3327b7d377f16e0aeabca54ca2c8906e23c5a77cdb19d2d4fb85f0bbd39d3cd"
        },
        {
            "type": "file",
            "name": "vendor/phpmailer/phpmailer/language/phpmailer.lang-sl.php",
            "size": 2577,
            "hash": "642ab71b9a02ee00abc39516e6d005957beff6dde91948155d0f25ce4f98630d"
        },
        {
            "type": "file",
            "name": "vendor/phpmailer/phpmailer/language/phpmailer.lang-sr.php",
            "size": 2301,
            "hash": "9982802bafa971f1d2e376fca86f8da86c7e43158ef6d3cb6f7c3ff51cc1c7e9"
        },
        {
            "type": "file",
            "name": "vendor/phpmailer/phpmailer/language/phpmailer.lang-sr_latn.php",
            "size": 1814,
            "hash": "0f67cf31fa3b5f2db2a2c74911096a73892377096c966923c0dc1fbbbc612a32"
        },
        {
            "type": "file",
            "name": "vendor/phpmailer/phpmailer/language/phpmailer.lang-sv.php",
            "size": 1610,
            "hash": "c1cb0390311cdff2f93ab37fff165b389fa74dca7f6341ce08240eca886b5ac3"
        },
        {
            "type": "file",
            "name": "vendor/phpmailer/phpmailer/language/phpmailer.lang-tl.php",
            "size": 1721,
            "hash": "48fa60bb2a88fdeb53960878fd0cdf88f7a59736a9efa487787b61de1c5d9db9"
        },
        {
            "type": "file",
            "name": "vendor/phpmailer/phpmailer/language/phpmailer.lang-tr.php",
            "size": 2606,
            "hash": "9f19069be7c25d8a0563ee535bbc57ebe3c65698b2af99320349a4002db99091"
        },
        {
            "type": "file",
            "name": "vendor/phpmailer/phpmailer/language/phpmailer.lang-uk.php",
            "size": 2282,
            "hash": "767609225673b2983c2cf7b208ae954d49d7728287da2c2cb859ca8c9273efd3"
        },
        {
            "type": "file",
            "name": "vendor/phpmailer/phpmailer/language/phpmailer.lang-ur.php",
            "size": 2265,
            "hash": "4404c38f4f64a1098678e0d30a62c63cd1dd56949fcc7f6ea89557fbf0693e06"
        },
        {
            "type": "file",
            "name": "vendor/phpmailer/phpmailer/language/phpmailer.lang-vi.php",
            "size": 1793,
            "hash": "3b5acbfceceb34f90dc7f905f044a51e48cce7f79cbf998b579b8bf00fa1fabc"
        },
        {
            "type": "file",
            "name": "vendor/phpmailer/phpmailer/language/phpmailer.lang-zh.php",
            "size": 1669,
            "hash": "ad235ae24994a85b63ff1bd2dadab9de1f2806a9764c162cf047459fa037814c"
        },
        {
            "type": "file",
            "name": "vendor/phpmailer/phpmailer/language/phpmailer.lang-zh_cn.php",
            "size": 2333,
            "hash": "cd53b733c64eeac233b140e33a6d58d337cd1ac28d6a5cd3231d87169f548c07"
        },
        {
            "type": "file",
            "name": "vendor/phpmailer/phpmailer/src/DSNConfigurator.php",
            "size": 6883,
            "hash": "429f5f0a962864ec7b67efd572c0f85cc0f33fd4585413d8dc80d41c8562399e"
        },
        {
            "type": "file",
            "name": "vendor/phpmailer/phpmailer/src/Exception.php",
            "size": 1256,
            "hash": "22ab858ae438d98f58f41f38ad2191d1b0d59570aebea0463a7948cfae1021b7"
        },
        {
            "type": "file",
            "name": "vendor/phpmailer/phpmailer/src/OAuth.php",
            "size": 3791,
            "hash": "44b2c9a3b6e538a65b90261251f197d700e2eb90d51d4944fb80577263210fb4"
        },
        {
            "type": "file",
            "name": "vendor/phpmailer/phpmailer/src/OAuthTokenProvider.php",
            "size": 1538,
            "hash": "f2318ea1b2841b2481b636e205c281a733f9de944a71ae403e0b59fa71219572"
        },
        {
            "type": "file",
            "name": "vendor/phpmailer/phpmailer/src/PHPMailer.php",
            "size": 187770,
            "hash": "835a15b6067083d7c92ea245c9ffab3ef23a8ac16bfe14a61e953741a661b9e2"
        },
        {
            "type": "file",
            "name": "vendor/phpmailer/phpmailer/src/POP3.php",
            "size": 12352,
            "hash": "42baf6cd05e05c8dba369cf7da411955b5e0b1c791828d538ca99b17335d7df9"
        },
        {
            "type": "file",
            "name": "vendor/phpmailer/phpmailer/src/SMTP.php",
            "size": 50097,
            "hash": "9bc105018f6ef2576c2c4a246a46fc41ada546111fc8fb1ffce86421af35e78c"
        }
    ]
}